NumInt/__init__.py
NumInt/gaussiana_compuesta.py
NumInt/gaussiana_compuesta_iterativa.py
NumInt/romberg.py
NumInt/simpson_compuesto.py
NumInt/simpson_compuesto_iterativo.py
NumInt/trapecio_compuesto.py
NumInt/trapecio_compuesto_iterativa.py
NumInt_ANPI-0.1.dist-info/METADATA
NumInt_ANPI-0.1.dist-info/WHEEL
NumInt_ANPI-0.1.dist-info/top_level.txt
NumInt_ANPI-0.1.dist-info/RECORD
